{"Name":"EqualsByValue","Description":"Determines whether two String objects have the same value. Null and String.Empty are considered equal values.","Author":"Omniscient Technology Inc","SubmittedOn":"10/5/2009 4:28:16 PM","Entries":["public static bool EqualsByValue(this string inString, string compared)\r\n        {\r\n            if (string.IsNullOrEmpty(inString) && string.IsNullOrEmpty(compared))\r\n                return true;\r\n\r\n            // If we get here, then \"compared\" necessarily contains data and therefore, strings are not equal.\r\n            if (inString == null)\r\n                return false;\r\n\r\n            // Turn down to standard equality check.\r\n            return inString.Equals(compared);\r\n        }","bool areEqual = a.EqualsByValue(b);"]}